imas_data_dictionary/__init__.py
imas_data_dictionary/_version.py
imas_data_dictionary/dd_doc.py
imas_data_dictionary/idsinfo.py
imas_data_dictionary/resources/schemas/data_dictionary.xml
imas_data_dictionary/resources/schemas/balance_of_plant/power_cycle_identifier.xml
imas_data_dictionary/resources/schemas/bolometer/camera_identifier.xml
imas_data_dictionary/resources/schemas/core_instant_changes/core_instant_changes_identifier.xml
imas_data_dictionary/resources/schemas/core_sources/core_source_identifier.xml
imas_data_dictionary/resources/schemas/core_transport/core_transport_identifier.xml
imas_data_dictionary/resources/schemas/ec_launchers/frame_DOF_identifier.xml
imas_data_dictionary/resources/schemas/edge_sources/edge_source_identifier.xml
imas_data_dictionary/resources/schemas/edge_transport/edge_transport_identifier.xml
imas_data_dictionary/resources/schemas/em_coupling/em_coupling_quantity_identifier.xml
imas_data_dictionary/resources/schemas/equilibrium/equilibrium_convergence_status_identifier.xml
imas_data_dictionary/resources/schemas/equilibrium/equilibrium_gs_deviation_identifier.xml
imas_data_dictionary/resources/schemas/equilibrium/equilibrium_profiles_2d_identifier.xml
imas_data_dictionary/resources/schemas/magnetics/magnetics_flux_loop_type_identifier.xml
imas_data_dictionary/resources/schemas/magnetics/magnetics_probe_type_identifier.xml
imas_data_dictionary/resources/schemas/magnetics/magnetics_rogowski_measured_identifier.xml
imas_data_dictionary/resources/schemas/mhd_linear/mhd_linear_ballooning_identifier.xml
imas_data_dictionary/resources/schemas/mhd_linear/mhd_linear_equations_identifier.xml
imas_data_dictionary/resources/schemas/mhd_linear/mhd_linear_model_identifier.xml
imas_data_dictionary/resources/schemas/mhd_linear/mhd_linear_perturbation_identifier.xml
imas_data_dictionary/resources/schemas/neutron_diagnostic/neutron_algorithm_identifier.xml
imas_data_dictionary/resources/schemas/neutron_diagnostic/neutron_event_identifier.xml
imas_data_dictionary-4.1.1.dist-info/licenses/LICENSE-CC-BY-ND
imas_data_dictionary-4.1.1.dist-info/licenses/LICENSE-LGPL
imas_data_dictionary-4.1.1.dist-info/METADATA
imas_data_dictionary-4.1.1.dist-info/WHEEL
imas_data_dictionary-4.1.1.dist-info/entry_points.txt
imas_data_dictionary-4.1.1.dist-info/top_level.txt
imas_data_dictionary-4.1.1.dist-info/RECORD
