Metadata-Version: 2.4
Name: imas-data-dictionary
Version: 4.1.1
Summary: The Data Dictionary is the implementation of the Data Model of ITER's Integrated Modelling & Analysis Suite (IMAS)
Author-email: ITER Organization <imas-support@iter.org>
License-Expression: LGPL-3.0+ AND CC-BY-ND-4.0
Project-URL: homepage, https://github.com/iterorganization/IMAS-Data-Dictionary
Keywords: IMAS,Data Dictionary,IDS
Classifier: Development Status :: 4 - Beta
Classifier: Intended Audience :: Developers
Classifier: Intended Audience :: Science/Research
Classifier: Programming Language :: Python :: 3
Classifier: Topic :: Scientific/Engineering :: Physics
Requires-Python: >=3.8
License-File: LICENSE-LGPL
License-File: LICENSE-CC-BY-ND
Requires-Dist: packaging
Provides-Extra: test
Requires-Dist: pytest>=6.0; extra == "test"
Requires-Dist: pytest-cov; extra == "test"
Dynamic: license-file
